{"919108006252": ["Manas Bam", 73, true], "447425939806": ["N Bam", 9, false], "917337610771": ["S\u00c5M\u00c3RTH", 67, true], "919880485164": ["sanjana", 73, true], "919986510691": ["Prakash", 73, true], "916366214819": ["Akshay", 73, true], "918971068402": ["Aadithya Hrudhay", 3, false], "919960528382": ["Radhika", 73, true], "919108796229": ["Aditya Agarwal", 73, true], "971563690841": ["Jyoti Nair", 73, true], "917619596206": ["Abhishek Mathur", 73, true], "917743824878": ["-", 73, true], "917815818928": ["Hitesh G", 73, true], "916360787318": ["Jovin Honey", 73, true], "917977322258": ["Prasad", 73, true], "919706015231": ["Swarup", 73, true], "919867832726": ["Manish Jalan", 73, true], "919971174089": ["DHRUV", 73, true], "447852570784": ["Kushal Paraskar", 23, false], "447412903447": ["Varsha", 73, true], "919739337390": ["Trishalla Mukherrjee", 73, true], "919845251812": ["B", 73, true], "919845089373": ["Komala Prabhu", 73, true], "918803519018": ["Ankita", 73, true], "447525925911": ["Sonalli R Sisodia \u00f0\u0178\u0152\u02c6", 73, true], "919845353350": ["Mallik", 73, true], "919845288554": ["Aai", 73, true], "919697023600": ["Adish", 73, true], "919003070594": ["Kritika * Harshika", 73, true], "916360575986": ["Sri Vidya", 73, true], "919663324541": ["HBK", 73, true], "918602313123": ["Shweta Iyer", 73, true], "919936638880": ["Devansh", 73, true], "919168645120": ["Puneeth Seth", 73, true], "919923659015": ["Arati Narwadkar", 73, true], "919923159011": ["Aadhya Narwadkar", 73, true], "919545518105": ["Rajendra Singh", 73, true], "919845609954": ["Savitha", 73, true], "447767576222": ["Mickey", 73, true], "919820298303": ["Devang Mehta", 73, true], "917008390516": ["Sripriya \u00f0\u0178\u0152\u00b8", 73, true], "19523347083": ["Prashant@stthomas", 72, true], "918762947810": ["Supratim Jash", 72, true], "916362705743": ["Ananya", 73, true], "919902126136": ["RNGowda", 72, true], "919340712856": ["Himanshu", 72, true], "919677692092": ["Anerud Uppalapati", 72, true], "918939922599": ["Sreevibhavan N", 72, true], "919812377351": [" ", 72, true], "919611892001": ["Smita Menon", 72, true], "919582228155": ["Prabhav", 72, true], "917382014518": ["Cc", 72, true], "447920116627": ["Kalpana Joshi", 72, true], "919449343850": ["Krishnamurthy D M", 72, true], "919972936132": ["Nisha N", 71, true], "919972383425": ["Lakshmi", 71, true], "919900092089": ["Shilpa Gangadhar", 71, true], "919480126442": ["RAJASEKHARA B M", 71, true], "918600158224": ["SJ\u263a\ufe0f", 71, true], "918527657775": ["Vijay", 71, true], "918447010815": ["Anil\ud83e\uddd0", 71, true], "918970022700": ["Raji Vijay", 71, true], "917899918369": ["Ramki", 71, true], "918073752864": ["Kausalya\u2728", 71, true], "917204494683": ["Rithika", 38, false], "447789997815": ["Nutan", 71, true], "919011793964": ["Anand", 71, true], "919627552410": ["saurabhbaruas", 71, true], "918618755463": ["My Name Is Vatsala... \ud83c\udf39\ud83c\udf39", 71, true], "919741466199": ["Santy", 71, true], "919449082464": ["Kamal", 71, true], "919220526309": ["Mayank Chandan", 71, true], "919620704400": ["Ankit", 71, true], "918698952318": ["Jatin", 71, true], "918088554967": ["Meghna", 71, true], "917975121326": ["Bhumika Honnali", 71, true], "919740377550": ["Sandeepvemal", 70, true], "919881652833": ["Sudhir Wamburkar", 71, true], "919900197231": ["Sunita Sharma Arora", 70, true], "919008944666": ["Gayathri", 70, true], "919422302559": ["Atul Dorge", 1, false], "919001138209": ["Nikhil Sharma", 70, true], "919415102307": ["Padmakar Bam", 70, true], "13175299421": ["Amrish Patel", 70, true], "919980377603": ["Neha Nair", 3, false], "919561513031": ["Surekha", 70, true], "917718873888": ["Soumya Acharya", 70, true], "919606807941": ["Nagarajaiah", 68, true], "447717307513": ["Gaurav", 70, true], "919850024025": ["..", 70, true], "917795885884": ["pooj\u2728", 70, true], "918867992947": ["Archisman", 70, true], "919881252057": ["soetrisno soetomo", 70, true], "918921869005": ["Manu S Nair", 70, true], "919370970316": ["Leena Vaidya", 70, true], "919011012057": ["PRATIBHA VAIDYA", 69, true], "919739311429": ["Krupsy", 69, true], "918310498878": ["Laksh", 69, true], "919739904248": ["Sai", 69, true], "status@broad": ["Hitesh G", 36, true], "919241477227": ["Gunasheela B", 69, true], "917040374262": ["ARK", 69, true], "919810930013": ["Rukmani Vijayakumar", 69, true], "919810103554": ["Bhavna", 69, true], "919415051533": ["\u0906\u092f\u094d\u0909\u0937 \u091c\u094d\u0906\u092f\u094d\u0905\u0938\u094d\u0905\u0935\u094d\u0906\u0932\u094d\u0905", 69, true], "919845102921": ["Harisha CS", 68, true], "918050977671": ["Yashu/Yash", 68, true], "918867798007": ["Harshavardhan Reniguntla", 68, true], "917259165886": ["Prema B P", 4, false], "919822374714": ["Bharati Kulkarni", 68, true], "919110459931": ["Savitha", 68, true], "917349372427": ["Nagashree", 68, true], "919611233854": ["GopalaKrishna C", 68, true], "919881674942": ["VINAY MULAY", 68, true], "919980753000": ["Vinod T", 68, true], "919663138368": ["Pooja", 68, true], "919480095544": ["sumana B H", 68, true], "919886325237": ["\ud83e\udd13\u0cb0\u0cc7\u0c96\u0cbe \u0ca8\u0cb0\u0cc7\u0c82\u0ca6\u0ccd\u0cb0\ud83d\ude0e", 68, true], "917892766396": ["Vb", 68, true], "919480088395": ["Thimmadasaiah Giriyappa", 68, true], "919630661054": ["Avinash", 68, true], "919886767157": ["Sapna", 68, true], "918892176844": ["I'm The Author Of My Life", 68, true], "918105961452": ["Yogesh", 68, true], "919972677995": ["Lohit", 3, false], "919483269093": ["Veda Shivakumar", 67, true], "917306229646": ["Hafis CP", 67, true], "919845022084": ["Karthik", 67, true], "919481827328": ["Paru", 67, true], "919886842915": ["Anmol", 67, true], "919986140708": ["Sahana Prasad", 66, true], "919880720393": ["Gowtham", 65, true], "919686540961": ["Divyashree", 65, true], "919521865519": ["Gautam", 65, true], "918073451030": ["~Hemu", 65, true], "919845364437": ["~Hemu\ud83d\udda4", 65, true], "919845017437": ["Kim Maini", 4, false], "916360903350": ["\ud835\udc03\ud835\udc21\ud835\udc1a\ud835\udc27\ud835\udc2e\ud835\udc2c\ud835\udc21 \ud835\udc0d\u26a1\ud83d\udde1\ufe0f\u2665\ufe0f", 65, true], "919513788079": ["Geetha Ammu", 65, true], "917760915138": ["Namitha", 65, true], "919916212520": ["Pushpalatha", 65, true], "917676722733": ["Anil Gowda", 65, true], "917899591764": ["\ud83d\ude07", 65, true], "919823330274": ["Rudra", 64, true], "919573378074": ["Santosh", 64, true], "916350316568": ["@kshay", 2, false], "917742053757": ["dinesh kumar khatri", 64, true], "919620657353": [".", 64, true], "919036609195": ["Sowmya R", 64, true], "919966039393": ["Pk", 63, true], "919886787749": ["Poornima\ud83d\ude0a", 63, true], "918341653259": ["Chaitanya", 63, true], "919860094772": ["Jyoti", 63, true], "919008034000": ["Jayashree", 63, true], "919742736421": ["aradhna", 63, true], "919884718183": ["Aditi Bagri", 63, true], "919311109058": ["R@J\u20ac$H", 63, true], "918073521035": ["WhatsAWordle", 62, true], "919923021789": ["Chhaya B", 61, true], "919923888272": ["Vishakha Kulkarni", 61, true], "919845272416": ["SV", 56, true], "31615030830@": ["TinTin", 19, true], "919652909907": ["Anjali", 9, false], "919844062345": ["Sowjanya", 55, true], "919483865751": ["\ud83d\udc97SuchiPramodh\ud83d\udc97", 55, true], "919560599931": ["Vipul", 55, true], "919620908038": ["Pradeep", 55, true], "917738651533": ["Bharati", 55, true], "919611134237": ["Shriya Agarwal", 55, true], "971509508960": ["Sujata Shah", 55, true], "919920715475": ["Manoj", 55, true], "919811366666": ["Anjali Sagar", 9, false], "919742094321": ["Renuka S R", 55, true], "919920556018": ["Prerna", 55, true], "919773577647": ["Khush!", 55, true], "919885500939": ["Usha", 55, true], "919986975368": ["harinikumar", 55, true], "918655040301": ["Meraki", 55, true], "919890100110": ["Surabhi Solanki", 55, true], "919986726788": ["Ravi R", 55, true], "971569907446": ["Neeraj Hinduja", 55, true], "917259303456": ["Dr Udhay Sidhu", 55, true], "919823257419": ["Purohit Vikas", 55, true], "919845838888": ["Rudra", 55, true], "917760644338": ["Kartikeya Agate", 55, true], "919910447974": ["Tulika", 55, true], "17322853989@": ["Swan", 19, true], "919840155258": ["E  Sethuraman", 55, true], "17734950793@": ["Roopam", 19, true], "919886510000": ["Monica Pirgal", 55, true], "919845043521": ["Mahima", 55, true], "919822096288": ["kalpana\ud83d\udc96", 55, true], "919818890890": ["Aditya", 55, true], "919739544451": ["Madhu", 55, true], "919764003384": ["Sachin R", 55, true], "919922467576": ["Amit P", 55, true], "917760233004": ["Poornima Kartik", 55, true], "919886000626": ["Sriram Pennathur", 55, true], "919885057960": ["Rahul", 55, true], "919822103913": ["Medha Dhekane", 55, true], "919980007455": ["Dr Rakesh", 55, true], "16128168646@": ["Dhanashri", 19, true], "919206717717": ["Nitten", 55, true], "919922034199": ["San\u2019", 55, true], "919480259712": ["Deepa J", 42, false], "919999239875": ["Dolly Pandey", 54, true], "919841012884": ["ALVIOXQULV", 54, true], "917904359826": ["Sreedavi Sethuraman", 54, true], "971505520277": ["Padma", 54, true], "919158219563": ["Padmanabh Kulkarni", 54, true], "919437960781": ["Binayak Shah", 54, true], "919830028118": ["Ajay Agarwal", 54, true], "919500088583": ["Padma", 54, true], "917904322633": ["AXTUAZACTXC", 54, true], "919830157550": ["Bimal Kumar Jain", 54, true], "918618702838": ["Dimple", 54, true], "919444655258": ["AQWEURIAK", 54, true], "919999291480": ["Ashok Kumar", 54, true], "919739978853": ["Seema", 54, true], "919980525575": ["Devang", 54, true], "919739401731": ["Manjula Prasad", 54, true], "919790704158": ["Aarav Krish Achan", 54, true], "919600104158": ["Fat Kat", 54, true], "919400944568": ["AQULIQAVOP", 53, true], "919341487380": ["sri", 53, true], "918454034445": ["Mukta \ud83d\udc9e", 53, true], "919845122773": ["Vipul Srivastava", 53, true], "919820207429": ["Parag Bhabal", 53, true], "919820404604": ["NL", 53, true], "918879701653": ["Rocky", 53, true], "917899549696": ["Vandana Supriya", 53, true], "919567047744": ["Gita Daily", 53, true], "919342533920": ["Aruna", 53, true], "919820357178": ["Laila Thachil", 53, true], "919223441813": ["Shamika Joglekar Khadye", 53, true], "919900101507": ["D. Srinivasan", 53, true], "918275254565": ["Vishwanath N Bendale", 53, true], "919811119875": ["Hari Pandey", 52, true], "15083141024@": ["Sujal Bhalakia", 19, true], "917406866222": ["Anupam joshi", 12, false], "918104115912": ["Ashutosh Nair", 52, true], "919448909844": ["Radha Rani", 52, true], "917349385119": ["Rajeshgaurav", 52, true], "919886188841": ["Sudhir K Varma", 52, true], "918310048417": ["akbusiness401", 52, true], "919686703027": ["Arti Rao", 4, false], "971503081250": ["Malu", 52, true], "919538423416": ["Rajendra Joshi", 52, true], "919886302127": ["Supriya Tandon", 51, true], "919900661624": ["Ankur", 51, true], "919620555502": ["Ramya Narasimhan", 51, true], "917022270910": ["damini", 51, true], "919894167671": ["Sarathy", 51, true], "919841631276": ["M. Lakshmi Narayanan", 51, true], "917411994435": ["LOKESH B C", 14, false], "919866867111": ["Vidya Mani", 51, true], "919959388868": ["Anusha", 51, true], "919880380008": ["Prerna\u2019s IPhone", 41, true], "919341254050": ["Anjana Chandak", 50, true], "919901759197": ["Rudresh", 50, true], "919164830917": ["$", 50, true], "919845077707": ["Sunanda Gupta", 50, true], "919860488808": ["Subhash Bhate", 50, true], "6598160947@s": ["Surajit Sen", 19, true], "919995515112": ["Aswathy $ B", 49, true], "919188951326": ["Relationship Manager PBB ", 2, false], "919741002351": ["Lalitanekraj", 49, true], "919746692388": ["Anand V", 49, true], "919496351344": ["Athira P Menon", 49, true], "919895255888": ["Nisha", 48, true], "15108629430@": ["Nitish Ratnam", 19, true], "6596432035@s": ["Sudesh Iyer", 19, true], "919880017383": ["Sudhajayanthp", 48, true], "917875592191": ["Deepali Wamburkar", 48, true], "919880069601": ["Surekha", 48, true], "918754443756": ["B", 48, true], "919445070973": ["Shankar", 48, true], "919920746946": ["Mona", 48, true], "919731177992": ["Giri Kuthethoor", 48, true], "919601162777": ["Mina", 48, true], "919048161097": ["Sneha", 48, true], "919844243752": ["Goutham Pathange", 47, true], "919480909605": ["Jyothi Shetty", 47, true], "96891369664@": ["Arun", 19, true], "919633715570": ["Aswani", 47, true], "971558485396": ["Vinutha Venkatesh", 47, true], "917760652150": ["Sindhura Nagendra", 45, true], "919845168971": ["Vara Lakshmi Prasanna", 11, false], "919951082595": ["Rj", 44, true], "919620009197": ["PGLK", 43, true], "919632399544": ["V \u00a3 \u00a3 \u20b9 \u00a3 $ H", 42, true], "917204666866": ["Hitech_RR547", 40, true], "919860488109": ["Anjali Bhate", 38, true], "918303566096": ["PRIYANSHU MAHESHWARI", 34, true], "917993060599": ["Smile", 29, true], "14082180768@": ["Manish Dixit", 16, true], "919739090062": ["\ud83c\udd3d\ud83c\udd30\ud83c\udd45\ud83c\udd34\ud83c\udd34\ud83c\udd3d \ud83c\udd3c\ud83c\udd30\ud83c\udd3a\ud83c\udd30\ud83c\udd3b\ud83c\udd34", 15, true], "919958430459": ["Gita Daily", 15, true], "919164300079": ["Harati", 15, true], "919448288833": ["T BHASKAR", 15, true], "447887626509": ["Mohana", 15, true], "919391274321": ["VIKAS AGARWAL", 15, true], "917624972468": ["Bharathi N", 15, true], "919591144455": ["Bhaskar Suruvu", 14, true], "918951025402": ["Gita Daily", 13, true], "919980090605": ["Sumangala", 13, true], "919902726519": ["Prema Subramanian.", 11, true], "918660318533": ["hrushikesh", 11, true], "919560742572": ["ShubhiG", 11, true], "6581755625@s": ["Gita Daily", 11, true], "917022784565": ["Karishnii Kuber", 11, true], "919902216268": ["Kiran K", 11, true], "919380052142": ["Gita Daily", 11, true], "917991203789": ["Nirmala Yadav", 11, true], "919884589896": ["naNda", 9, true]}
