{
    "verse": "\u0930\u0941\u0926\u094d\u0930\u093e\u0926\u093f\u0924\u094d\u092f\u093e \u0935\u0938\u0935\u094b \u092f\u0947 \u091a \u0938\u093e\u0927\u094d\u092f\u093e\n \u0935\u093f\u0936\u094d\u0935\u0947\u093d\u0936\u094d\u0935\u093f\u0928\u094c \u092e\u0930\u0941\u0924\u0936\u094d\u091a\u094b\u0937\u094d\u092e\u092a\u093e\u0936\u094d\u091a |\n\u0917\u0928\u094d\u0927\u0930\u094d\u0935\u092f\u0915\u094d\u0937\u093e\u0938\u0941\u0930\u0938\u093f\u0926\u094d\u0927\u0938\u0919\u094d\u0918\u093e\n\u0935\u0940\u0915\u094d\u0937\u0928\u094d\u0924\u0947 \u0924\u094d\u0935\u093e\u0902 \u0935\u093f\u0938\u094d\u092e\u093f\u0924\u093e\u0936\u094d\u091a\u0948\u0935 \u0938\u0930\u094d\u0935\u0947 || 22||\n",
    "transliteration": "rudr\u0101dity\u0101 vasavo ye cha s\u0101dhy\u0101vi\u015bhve \u2019\u015bhvinau maruta\u015bh cho\u1e63hmap\u0101\u015bh chagandharva-yak\u1e63h\u0101sura-siddha-sa\u1e45gh\u0101v\u012bk\u1e63hante tv\u0101\u1e41 vismit\u0101\u015bh chaiva sarve",
    "audio": "https://www.holy-bhagavad-gita.org/public/audio/011_022.mp3",
    "word meanings": "\nrudra\u2014a form of Lord Shiv; \u0101dity\u0101\u1e25\u2014the adityas; vasava\u1e25\u2014the vasus; ye\u2014these; cha\u2014and; s\u0101dhy\u0101\u1e25\u2014the sadhyas; vi\u015bhve\u2014the vishvadevas; a\u015bhvinau\u2014the Ashvini Kumars; maruta\u1e25\u2014the maruts; cha\u2014and; u\u1e63hma-p\u0101\u1e25\u2014the ancestors; cha\u2014and; gandharva\u2014gandharvas; yak\u1e63ha\u2014the yakshas; asura\u2014the demons; siddha\u2014the perfected beings; sa\u1e45gh\u0101\u1e25\u2014the assemblies; v\u012bk\u1e63hante\u2014are beholding; tv\u0101m\u2014you; vismit\u0101\u1e25\u2014in wonder; cha\u2014and; eva\u2014verily; sarve\u2014all\n",
    "translation": "The Rudras, Adityas, Vasus, Sadhyas, Visvedevas, the two Asvins, Maruts, the manes and the hosts of celestial singers, Yakshas, demons and the perfected ones, are all looking at Thee, in great amazement.",
    "commentary": "\nAll these personalities receive their positions by the power of God and they discharge their respective duties in reverence to the Laws of Creation. Thus, they are all mentioned as beholding the cosmic form of God with wonder.\n",
    "next shlok": 23,
    "new_commentary": "\nAll these personalities receive their positions by the power of God and they discharge their respective duties in reverence to the Laws of Creation. Thus, they are all mentioned as beholding the cosmic form of God with wonder.\n",
    "newest_commentary": "\nAll these personalities receive their positions by the power of God and they discharge their respective duties in reverence to the Laws of Creation. Thus, they are all mentioned as beholding the cosmic form of God with wonder.\n"
}